comfyvault/__init__.py
comfyvault/cli.py
comfyvault/core.py
comfyvault/crypto.py
comfyvault/storage.py
comfyvault/utils.py
comfyvault-0.1.1.dist-info/entry_points.txt
comfyvault-0.1.1.dist-info/licenses/LICENSE
comfyvault-0.1.1.dist-info/METADATA
comfyvault-0.1.1.dist-info/WHEEL
comfyvault-0.1.1.dist-info/RECORD
