Metadata-Version: 2.4
Name: comfyvault
Version: 0.1.1
Summary: A secure, terminal-only password manager.
License: MIT
License-File: LICENSE
Author: Abderrahman YOUABD
Author-email: youabd50@gmail.com
Requires-Python: >=3.10,<4.0
Classifier: Environment :: Console
Classifier: License :: OSI Approved :: MIT License
Classifier: Operating System :: OS Independent
Classifier: Programming Language :: Python :: 3
Classifier: Programming Language :: Python :: 3.10
Classifier: Programming Language :: Python :: 3.11
Classifier: Programming Language :: Python :: 3.12
Classifier: Programming Language :: Python :: 3.13
Classifier: Programming Language :: Python :: 3.14
Classifier: Topic :: Security :: Cryptography
Requires-Dist: click (>=8.1.0,<9.0.0)
Requires-Dist: cryptography (>=41.0.0,<42.0.0)
Requires-Dist: pyperclip (>=1.8.2,<2.0.0)
Requires-Dist: rich (>=13.0.0,<14.0.0)
